dlio_benchmark/__init__.py
dlio_benchmark/main.py
dlio_benchmark/postprocessor.py
dlio_benchmark/checkpointing/__init__.py
dlio_benchmark/checkpointing/base_checkpointing.py
dlio_benchmark/checkpointing/checkpointing_factory.py
dlio_benchmark/checkpointing/pytorch_checkpointing.py
dlio_benchmark/checkpointing/tf_checkpointing.py
dlio_benchmark/common/__init__.py
dlio_benchmark/common/constants.py
dlio_benchmark/common/data_structures.py
dlio_benchmark/common/enumerations.py
dlio_benchmark/common/error_code.py
dlio_benchmark/computation/__init__.py
dlio_benchmark/computation/asynchronous_computation.py
dlio_benchmark/computation/computation_factory.py
dlio_benchmark/computation/computation_handler.py
dlio_benchmark/computation/no_computation.py
dlio_benchmark/computation/synchronous_computation.py
dlio_benchmark/configs/__init__.py
dlio_benchmark/configs/config.yaml
dlio_benchmark/configs/hydra/help/dlio_benchmark_help.yaml
dlio_benchmark/configs/hydra/job_logging/custom.yaml
dlio_benchmark/configs/workload/bert_v100.yaml
dlio_benchmark/configs/workload/cosmoflow_a100.yaml
dlio_benchmark/configs/workload/cosmoflow_h100.yaml
dlio_benchmark/configs/workload/cosmoflow_v100.yaml
dlio_benchmark/configs/workload/default.yaml
dlio_benchmark/configs/workload/dlrm.yaml
dlio_benchmark/configs/workload/megatron_deepspeed.yaml
dlio_benchmark/configs/workload/resnet50_a100.yaml
dlio_benchmark/configs/workload/resnet50_h100.yaml
dlio_benchmark/configs/workload/resnet50_tf.yaml
dlio_benchmark/configs/workload/resnet50_v100.yaml
dlio_benchmark/configs/workload/unet3d_a100.yaml
dlio_benchmark/configs/workload/unet3d_h100.yaml
dlio_benchmark/configs/workload/unet3d_v100.yaml
dlio_benchmark/data_generator/__init__.py
dlio_benchmark/data_generator/csv_generator.py
dlio_benchmark/data_generator/data_generator.py
dlio_benchmark/data_generator/generator_factory.py
dlio_benchmark/data_generator/hdf5_generator.py
dlio_benchmark/data_generator/indexed_binary_generator.py
dlio_benchmark-2.0.0.dist-info/LICENSE
dlio_benchmark-2.0.0.dist-info/METADATA
dlio_benchmark-2.0.0.dist-info/WHEEL
dlio_benchmark-2.0.0.dist-info/dependency_links.txt
dlio_benchmark-2.0.0.dist-info/entry_points.txt
dlio_benchmark-2.0.0.dist-info/top_level.txt
dlio_benchmark-2.0.0.dist-info/RECORD
