Metadata-Version: 2.1
Name: dlio_benchmark
Version: 2.0.0
Summary: An I/O benchmark for deep Learning applications
Home-page: https://github.com/argonne-lcf/dlio_benchmark
Author: Huihuo Zheng, Hariharan Devarajan (Hari)
Author-email: zhenghh04@gmail.com, mani.hariharan@gmail.com
Project-URL: Bug Reports, https://github.com/argonne-lcf/dlio_benchmark/issues
Project-URL: Source, https://github.com/argonne-lcf/dlio_benchmark
Keywords: deep learning,I/O,benchmark,NPZ,pytorch benchmark,tensorflow benchmark
Classifier: Development Status :: 5 - Production/Stable
Classifier: Intended Audience :: Science/Research
Classifier: Topic :: Software Development :: Build Tools
Classifier: License :: OSI Approved :: Apache Software License
Classifier: Programming Language :: Python :: 3.7
Classifier: Programming Language :: Python :: 3.8
Classifier: Programming Language :: Python :: 3.9
Classifier: Programming Language :: Python :: 3.10
Classifier: Programming Language :: Python :: 3.11
Classifier: Programming Language :: Python :: 3.12
Classifier: Programming Language :: Python :: 3 :: Only
License-File: LICENSE
Requires-Dist: Pillow >=9.3.0
Requires-Dist: PyYAML >=6.0.0
Requires-Dist: h5py >=3.11.0
Requires-Dist: mpi4py >=3.1.4
Requires-Dist: numpy >=1.23.5
Requires-Dist: omegaconf >=2.2.0
Requires-Dist: pandas >=1.5.1
Requires-Dist: psutil >=5.9.8
Requires-Dist: pydftracer ==1.0.2
Requires-Dist: hydra-core >=1.3.2
Requires-Dist: nvidia-dali-cuda110 >=1.34.0
Requires-Dist: tensorflow >=2.11.0
Requires-Dist: torch >=2.2.0
Requires-Dist: torchaudio
Requires-Dist: torchvision
Provides-Extra: test
Requires-Dist: pytest ; extra == 'test'
